optool/VERSION
optool/__init__.py
optool/conversions.py
optool/core.py
optool/languages.py
optool/logging.py
optool/math.py
optool/parallel.py
optool/py.typed
optool/uom.py
optool/util.py
optool/fields/__init__.py
optool/fields/callables.py
optool/fields/containers.py
optool/fields/misc.py
optool/fields/numeric.py
optool/fields/quantities.py
optool/fields/symbolic.py
optool/fields/tabular.py
optool/fields/util.py
optool/optimization/__init__.py
optool/optimization/constraints.py
optool/optimization/helpers.py
optool/optimization/ode.py
optool/optimization/problem.py
optool/optimization/variables.py
optool/serialization/__init__.py
optool/serialization/datetime_objects.py
optool/serialization/numpy_objects.py
optool/serialization/pandas_objects.py
optool/serialization/pint_objects.py
optool-0.9.0.dist-info/LICENSE.txt
optool-0.9.0.dist-info/METADATA
optool-0.9.0.dist-info/WHEEL
optool-0.9.0.dist-info/top_level.txt
optool-0.9.0.dist-info/RECORD
