Metadata-Version: 2.1
Name: optool
Version: 0.9.0
Summary: Optimization tools
Author: Andreas Ritter
Author-email: anritter@idsc.mavt.ethz.ch
License: MIT
Project-URL: Source, https://gitlab.com/ocsept/optool
Project-URL: Documentation, https://ocsept.gitlab.io/optool
Project-URL: API, https://ocsept.gitlab.io/optool/api/index.html
Keywords: Serialization,Numerical optimization,Units of measurement,JSON,Pydantic,Pint,CasADi
Platform: any
Classifier: Development Status :: 4 - Beta
Classifier: Programming Language :: Python
Requires-Python: >=3.9.10
License-File: LICENSE.txt
Requires-Dist: casadi
Requires-Dist: humanize
Requires-Dist: loguru
Requires-Dist: numpy
Requires-Dist: pandas
Requires-Dist: pint
Requires-Dist: pint-pandas
Requires-Dist: pydantic (<2.0)
Requires-Dist: multiprocess
Provides-Extra: testing
Requires-Dist: setuptools ; extra == 'testing'
Requires-Dist: pytest ; extra == 'testing'
Requires-Dist: pytest-cov ; extra == 'testing'
